app/deploy.py
app/main.py
app/models.py
app/settings.py
app/dify/__init__.py
app/dify/dify_client.py
app/dify/models.py
app/dify/workflow_tool.py
app/mybot/__init__.py
app/mybot/common.py
app/mybot/prompts.py
app/mybot/handlers/__init__.py
app/mybot/handlers/message_handler.py
app/mybot/handlers/command_handler/__init__.py
app/mybot/handlers/command_handler/help_command.py
app/mybot/handlers/command_handler/parse_command.py
app/mybot/handlers/command_handler/search_command.py
app/mybot/handlers/command_handler/start_command.py
app/mybot/handlers/command_handler/zlib_command.py
app/mybot/handlers/command_handler/templates/help.txt
app/mybot/handlers/command_handler/templates/instant_view.txt
app/mybot/services/__init__.py
app/mybot/services/context_service.py
app/mybot/services/dify_service.py
app/mybot/services/instant_view_service.py
app/mybot/services/interaction_service.py
app/mybot/services/response_service.py
app/plugins/001.collect_wiki.ipynb
app/plugins/__init__.py
app/plugins/commit_message_generator/__init__.py
app/plugins/commit_message_generator/node.py
app/plugins/instant_view_generator/__init__.py
app/plugins/instant_view_generator/node.py
app/plugins/social_parser/__init__.py
app/plugins/social_parser/base.py
app/plugins/social_parser/xhs.py
app/plugins/zlib_access_points/__init__.py
app/plugins/zlib_access_points/crud.py
app/plugins/zlib_access_points/node.py
app/utils/__init__.py
app/utils/image_compressor.py
app/utils/init_log.py
qin2dimbot-0.5.2.dist-info/METADATA
qin2dimbot-0.5.2.dist-info/WHEEL
qin2dimbot-0.5.2.dist-info/licenses/LICENSE
qin2dimbot-0.5.2.dist-info/RECORD
