Metadata-Version: 2.4
Name: qin2dimbot
Version: 0.5.2
Summary: Add your description here
License-File: LICENSE
Requires-Python: >=3.12
Requires-Dist: apscheduler>=3.11.0
Requires-Dist: bs4>=0.0.2
Requires-Dist: httpx-sse>=0.4.1
Requires-Dist: httpx>=0.28.1
Requires-Dist: loguru>=0.7.3
Requires-Dist: markdown>=3.8.2
Requires-Dist: mdx-truly-sane-lists>=1.3
Requires-Dist: pillow>=11.3.0
Requires-Dist: psycopg2-binary>=2.9.10
Requires-Dist: pydantic-settings>=2.10.1
Requires-Dist: python-telegram-bot[all]>=22.2
Requires-Dist: sqlalchemy-utils>=0.41.2
Requires-Dist: sqlalchemy>=2.0.41
Requires-Dist: telegraph[aio]>=2.2.0
Requires-Dist: yt-dlp[default]>=2025.7.21
